fundamental/__init__.py
fundamental/fundamental.py
fundamental-0.1.1.18.dist-info/LICENSE.txt
fundamental-0.1.1.18.dist-info/METADATA
fundamental-0.1.1.18.dist-info/WHEEL
fundamental-0.1.1.18.dist-info/top_level.txt
fundamental-0.1.1.18.dist-info/RECORD
