Metadata-Version: 2.1
Name: fundamental
Version: 0.1.1.18
Summary: Data frame downloader for fundamental financial
Home-page: https://github.com/steven2K19/fundamental
Author: Steven Wang
Author-email: steven.wang0619@gmail.com
License: UNKNOWN
Platform: UNKNOWN
Classifier: Programming Language :: Python :: 3
Classifier: License :: OSI Approved :: MIT License
Requires-Dist: numpy
Requires-Dist: pandas
Requires-Dist: yfinance
Requires-Dist: datetime
Requires-Dist: lxml
Requires-Dist: pandas-market-calendars
